botvac_tools
